karrio/mappers/dhl_parcel_de/__init__.py
karrio/mappers/dhl_parcel_de/mapper.py
karrio/mappers/dhl_parcel_de/proxy.py
karrio/mappers/dhl_parcel_de/settings.py
karrio/plugins/dhl_parcel_de/__init__.py
karrio/providers/dhl_parcel_de/__init__.py
karrio/providers/dhl_parcel_de/error.py
karrio/providers/dhl_parcel_de/tracking.py
karrio/providers/dhl_parcel_de/units.py
karrio/providers/dhl_parcel_de/utils.py
karrio/providers/dhl_parcel_de/pickup/__init__.py
karrio/providers/dhl_parcel_de/pickup/cancel.py
karrio/providers/dhl_parcel_de/pickup/create.py
karrio/providers/dhl_parcel_de/shipment/__init__.py
karrio/providers/dhl_parcel_de/shipment/cancel.py
karrio/providers/dhl_parcel_de/shipment/create.py
karrio/schemas/dhl_parcel_de/__init__.py
karrio/schemas/dhl_parcel_de/cancel_response.py
karrio/schemas/dhl_parcel_de/error_response.py
karrio/schemas/dhl_parcel_de/pickup_cancel_response.py
karrio/schemas/dhl_parcel_de/pickup_request.py
karrio/schemas/dhl_parcel_de/pickup_response.py
karrio/schemas/dhl_parcel_de/pickup_status_response.py
karrio/schemas/dhl_parcel_de/shipping_request.py
karrio/schemas/dhl_parcel_de/shipping_response.py
karrio/schemas/dhl_parcel_de/tracking_request.py
karrio/schemas/dhl_parcel_de/tracking_response.py
vendors/test_tracking_live.py
karrio_dhl_parcel_de-2026.1.4.dist-info/METADATA
karrio_dhl_parcel_de-2026.1.4.dist-info/WHEEL
karrio_dhl_parcel_de-2026.1.4.dist-info/entry_points.txt
karrio_dhl_parcel_de-2026.1.4.dist-info/top_level.txt
karrio_dhl_parcel_de-2026.1.4.dist-info/RECORD
